muslimDeen/__init__.py
muslimDeen/config.py
muslimDeen/datasetmodel.py
muslimDeen/handle_exception.py
muslimDeen/interface.py
muslimDeen/meta_model_quran.py
muslimDeen/meta_quran_reader.py
muslimDeen/metasurahs.py
muslimDeen/model.py
muslimDeen/model_name.py
muslimDeen/model_surah.py
muslimDeen/quran_reader_base.py
muslimDeen/service.py
muslimDeen/utils_model.py
muslimdeen-1.0.2.dist-info/METADATA
muslimdeen-1.0.2.dist-info/WHEEL
muslimdeen-1.0.2.dist-info/top_level.txt
muslimdeen-1.0.2.dist-info/RECORD
