Metadata-Version: 2.1
Name: muslimdeen
Version: 1.0.2
Summary: MuslimDeen: Package pour gérer les sourates et le coran
Home-page: https://gitlab.com/misternobody01/package_muslimdeen.git
Author: personne monsieur
Author-email: monsieurnobody01@gmail.com
Classifier: Programming Language :: Python :: 3
Classifier: License :: OSI Approved :: MIT License
Classifier: Operating System :: OS Independent
Requires-Python: >=3.6
Requires-Dist: numpy==2.2.0
Requires-Dist: pandas==2.2.3
Requires-Dist: requests==2.32.3
Requires-Dist: python-dateutil==2.9.0.post0
Requires-Dist: pytz==2024.2
Requires-Dist: sentence-transformers==3.3.1
Requires-Dist: faiss-cpu==1.9.0.post1
Requires-Dist: regex==2024.11.6
Requires-Dist: rapidfuzz==3.10.1
Requires-Dist: symspellpy==6.7.8
Requires-Dist: torch==2.5.1
Requires-Dist: transformers==4.47.0
